{
"type": "FeatureCollection",
"name": "bbb",
"crs": { "type": "name", "properties": { "name": "urn:ogc:def:crs:OGC:1.3:CRS84" } },
"features": [
{ "type": "Feature", "properties": { "Тип": "Объект недвижимости", "Вид": "Земельный участок", "Кадастровый номер": "72:23:0216003:358", "Кадастровый квартал": "72:23:0216003", "Адрес": "обл. Тюменская, г. Тюмень, ул. Луначарского, 2, ул. Луначарского, 2, корпуса 1, 2, 3, 4, 5", "Площадь уточненная": "28 902 кв. м", "Статус": "Ранее учтенный", "Категория земель": "Земли населённых пунктов", "Разрешенное использование": "под комплекс зданий университета", "Форма собственности": "Собственность публично-правовых образований", "Кадастровая стоимость": "41 544 890,88 руб.", "дата определения": "01.01.2022", "дата утверждения": "-", "дата внесения сведений": "16.03.2023", "дата применения": "01.01.2023" }, "geometry": { "type": "Point", "coordinates": [ 65.514890906917543, 57.167188473373102 ] } }
]
}
